ZhihuZhoukanChengxuRenshengZongdi31Qi/README.md
ZhihuZhoukanChengxuRenshengZongdi31Qi/__init__.py
ZhihuZhoukanChengxuRenshengZongdi31Qi/__main__.py
ZhihuZhoukanChengxuRenshengZongdi31Qi/file.epub
ZhihuZhoukanChengxuRenshengZongdi31Qi/index.html
ZhihuZhoukanChengxuRenshengZongdi31Qi/css/__init__.py
ZhihuZhoukanChengxuRenshengZongdi31Qi/css/annotations.css
ZhihuZhoukanChengxuRenshengZongdi31Qi/css/main.css
ZhihuZhoukanChengxuRenshengZongdi31Qi/css/normalize.css
ZhihuZhoukanChengxuRenshengZongdi31Qi/css/popup.css
ZhihuZhoukanChengxuRenshengZongdi31Qi/font/__init__.py
ZhihuZhoukanChengxuRenshengZongdi31Qi/font/fontello.eot
ZhihuZhoukanChengxuRenshengZongdi31Qi/font/fontello.svg
ZhihuZhoukanChengxuRenshengZongdi31Qi/font/fontello.ttf
ZhihuZhoukanChengxuRenshengZongdi31Qi/font/fontello.woff
ZhihuZhoukanChengxuRenshengZongdi31Qi/img/__init__.py
ZhihuZhoukanChengxuRenshengZongdi31Qi/img/annotator-glyph-sprite.png
ZhihuZhoukanChengxuRenshengZongdi31Qi/img/annotator-icon-sprite.png
ZhihuZhoukanChengxuRenshengZongdi31Qi/img/apple-touch-icon.png
ZhihuZhoukanChengxuRenshengZongdi31Qi/img/cancelfullscreen.png
ZhihuZhoukanChengxuRenshengZongdi31Qi/img/close.png
ZhihuZhoukanChengxuRenshengZongdi31Qi/img/fullscreen.png
ZhihuZhoukanChengxuRenshengZongdi31Qi/img/loader.gif
ZhihuZhoukanChengxuRenshengZongdi31Qi/img/menu-icon.png
ZhihuZhoukanChengxuRenshengZongdi31Qi/img/save.png
ZhihuZhoukanChengxuRenshengZongdi31Qi/img/saved.png
ZhihuZhoukanChengxuRenshengZongdi31Qi/img/settings-s.png
ZhihuZhoukanChengxuRenshengZongdi31Qi/img/settings.png
ZhihuZhoukanChengxuRenshengZongdi31Qi/img/star.png
ZhihuZhoukanChengxuRenshengZongdi31Qi/js/__init__.py
ZhihuZhoukanChengxuRenshengZongdi31Qi/js/epub.js
ZhihuZhoukanChengxuRenshengZongdi31Qi/js/epub.min.js
ZhihuZhoukanChengxuRenshengZongdi31Qi/js/epub.min.map
ZhihuZhoukanChengxuRenshengZongdi31Qi/js/hooks.min.js
ZhihuZhoukanChengxuRenshengZongdi31Qi/js/hooks.min.map
ZhihuZhoukanChengxuRenshengZongdi31Qi/js/reader.js
zhihu_zhoukan_chengxu_rensheng_zongdi_31_qi-2024.3.2.0.dist-info/METADATA
zhihu_zhoukan_chengxu_rensheng_zongdi_31_qi-2024.3.2.0.dist-info/WHEEL
zhihu_zhoukan_chengxu_rensheng_zongdi_31_qi-2024.3.2.0.dist-info/entry_points.txt
zhihu_zhoukan_chengxu_rensheng_zongdi_31_qi-2024.3.2.0.dist-info/top_level.txt
zhihu_zhoukan_chengxu_rensheng_zongdi_31_qi-2024.3.2.0.dist-info/RECORD
